dagster_contrib_notdiamond/__init__.py
dagster_contrib_notdiamond/py.typed
dagster_contrib_notdiamond/resources.py
dagster_contrib_notdiamond-0.1.2.dist-info/METADATA
dagster_contrib_notdiamond-0.1.2.dist-info/WHEEL
dagster_contrib_notdiamond-0.1.2.dist-info/top_level.txt
dagster_contrib_notdiamond-0.1.2.dist-info/RECORD
