Metadata-Version: 2.1
Name: dagster-contrib-notdiamond
Version: 0.1.2
Summary: Dagster integration with Not Diamond
Requires-Python: >=3.9
Requires-Dist: dagster>=1.8.0
Requires-Dist: notdiamond
